wrattler_data_store/__init__.py
wrattler_data_store/data_store.py
wrattler_data_store/exceptions.py
wrattler_data_store/storage.py
wrattler_data_store/utils.py
wrattler_data_store-0.5.2.dist-info/METADATA
wrattler_data_store-0.5.2.dist-info/WHEEL
wrattler_data_store-0.5.2.dist-info/entry_points.txt
wrattler_data_store-0.5.2.dist-info/top_level.txt
wrattler_data_store-0.5.2.dist-info/RECORD
